{"GlobalPropertiesHash":"5DhiAnRlIXMdjsrEsMuEtqJ0xlvYuTG5v1Kpl8xOOgg=","FingerprintPatternsHash":"gq3WsqcKBUGTSNle7RKKyXRIwh7M8ccEqOqYvIzoM04=","PropertyOverridesHash":"8ZRc1sGeVrPBx4lD717BgRaQekyh78QKV9SKsdt638U=","InputHashes":["5pqKh2Xyvdwo\u002BZTbVOAC4bourKWt\u002B/MAiiyZGEPnztA=","7Od6ejf8t5FNW29/0SY3Xoeq/Rmz7mt9ZOyAT0O1olY=","pmD8R0s/TtT3e/qFBD1tckJ4QlWy3F1vdz4mC9Ag7Q4=","lyaNoO2tkMA2VOOFgjhXro9K6h96NgVSUp4ouA0rGJs="],"CachedAssets":{"5pqKh2Xyvdwo\u002BZTbVOAC4bourKWt\u002B/MAiiyZGEPnztA=":{"Identity":"C:\\Users\\usuario\\source\\repos\\api_Kaosnet\\api_Kaosnet\\wwwroot\\uploads\\77d40e12-f717-42a4-8612-2c08d167d261.png","SourceId":"api_Kaosnet","SourceType":"Discovered","ContentRoot":"C:\\Users\\usuario\\source\\repos\\api_Kaosnet\\api_Kaosnet\\wwwroot\\","BasePath":"_content/api_Kaosnet","RelativePath":"uploads/77d40e12-f717-42a4-8612-2c08d167d261#[.{fingerprint}]?.png","AssetKind":"All","AssetMode":"All","AssetRole":"Primary","AssetMergeBehavior":null,"AssetMergeSource":"","RelatedAsset":null,"AssetTraitName":null,"AssetTraitValue":null,"Fingerprint":"89azbow2rw","Integrity":"rOl77zo/1BhR6/ZoZoin/zh2xhDWRsM3FZobV7GRK44=","CopyToOutputDirectory":"Never","CopyToPublishDirectory":"PreserveNewest","OriginalItemSpec":"wwwroot\\uploads\\77d40e12-f717-42a4-8612-2c08d167d261.png","FileLength":65632,"LastWriteTime":"2025-09-18T16:42:58.7729827+00:00"},"7Od6ejf8t5FNW29/0SY3Xoeq/Rmz7mt9ZOyAT0O1olY=":{"Identity":"C:\\Users\\usuario\\source\\repos\\api_Kaosnet\\api_Kaosnet\\wwwroot\\uploads\\cb6b8100-f3a7-4329-a2ad-f43d0d9dd877.png","SourceId":"api_Kaosnet","SourceType":"Discovered","ContentRoot":"C:\\Users\\usuario\\source\\repos\\api_Kaosnet\\api_Kaosnet\\wwwroot\\","BasePath":"_content/api_Kaosnet","RelativePath":"uploads/cb6b8100-f3a7-4329-a2ad-f43d0d9dd877#[.{fingerprint}]?.png","AssetKind":"All","AssetMode":"All","AssetRole":"Primary","AssetMergeBehavior":null,"AssetMergeSource":"","RelatedAsset":null,"AssetTraitName":null,"AssetTraitValue":null,"Fingerprint":"89azbow2rw","Integrity":"rOl77zo/1BhR6/ZoZoin/zh2xhDWRsM3FZobV7GRK44=","CopyToOutputDirectory":"Never","CopyToPublishDirectory":"PreserveNewest","OriginalItemSpec":"wwwroot\\uploads\\cb6b8100-f3a7-4329-a2ad-f43d0d9dd877.png","FileLength":65632,"LastWriteTime":"2025-09-18T16:36:54.7785964+00:00"}},"CachedCopyCandidates":{}}